keke/__init__.py
keke/py.typed
keke/tests/__init__.py
keke/tests/__main__.py
keke/tests/core.py
keke-0.1.4.dist-info/LICENSE
keke-0.1.4.dist-info/METADATA
keke-0.1.4.dist-info/WHEEL
keke-0.1.4.dist-info/top_level.txt
keke-0.1.4.dist-info/RECORD
