Metadata-Version: 2.1
Name: keke
Version: 0.1.4
Summary: Easy profiling in chrome trace format
Home-page: https://github.com/keke-tracing/keke
Author: Tim Hatch
Author-email: tim@timhatch.com
License: MIT
Requires-Python: >=3.8
License-File: LICENSE
